pysymbolscanner/__init__.py
pysymbolscanner/__main__.py
pysymbolscanner/command_line.py
pysymbolscanner/const.py
pysymbolscanner/index_definitions.py
pysymbolscanner/infobox.py
pysymbolscanner/scanner.py
pysymbolscanner/stock.py
pysymbolscanner/utils.py
pysymbolscanner/wiki.py
pysymbolscanner/word_score.py
pysymbolscanner/yahoo.py
pysymbolscanner-1.13.2.dist-info/LICENSE
pysymbolscanner-1.13.2.dist-info/METADATA
pysymbolscanner-1.13.2.dist-info/WHEEL
pysymbolscanner-1.13.2.dist-info/RECORD
