Metadata-Version: 2.1
Name: pysymbolscanner
Version: 1.13.2
Summary: wiki stock information crawler
License: MIT
Author: SlashGordon
Author-email: slash.gordon.dev@gmail.com
Requires-Python: >=3.11,<4.0
Classifier: License :: OSI Approved :: MIT License
Classifier: Programming Language :: Python :: 3
Classifier: Programming Language :: Python :: 3.11
Classifier: Programming Language :: Python :: 3.12
Requires-Dist: PyYAML (==6.0)
Requires-Dist: Unidecode (==1.3.6)
Requires-Dist: pandas (==1.5.1)
Requires-Dist: pycountry (==22.3.5)
Requires-Dist: pytickersymbols (>=1.13.0,<2.0.0)
Requires-Dist: toolz (>=0.12.0,<0.13.0)
Requires-Dist: uplink (==0.9.7)
Requires-Dist: wikipedia (==1.4.0)
Requires-Dist: wptools (==0.4.17)
